flowtracks/__init__.py
flowtracks/an_scene.py
flowtracks/analysis.py
flowtracks/format_docstrings.py
flowtracks/future_idea_xarray_dask_zarr.py
flowtracks/graphics.py
flowtracks/interpolation.py
flowtracks/io.py
flowtracks/pairs.py
flowtracks/particle.py
flowtracks/scene.py
flowtracks/sequence.py
flowtracks/smoothing.py
flowtracks/trajectory.py
flowtracks-1.1.1.data/data/flowtracks-examples/hdf5_scene_analysis.ipynb
flowtracks-1.1.1.data/data/flowtracks-examples/linking_trajectories.ipynb
flowtracks-1.1.1.data/data/flowtracks-examples/repeated_interpolation.ipynb
flowtracks-1.1.1.data/scripts/analyse_fhdf.py
flowtracks-1.1.1.dist-info/licenses/LICENSE.txt
flowtracks-1.1.1.dist-info/METADATA
flowtracks-1.1.1.dist-info/WHEEL
flowtracks-1.1.1.dist-info/top_level.txt
flowtracks-1.1.1.dist-info/RECORD
