Metadata-Version: 2.4
Name: flowtracks
Version: 1.1.1
Summary: Library for handling of PTV trajectory database.
Home-page: https://github.com/OpenPTV/postptv
Author: Yosef Meller
Author-email: Yosef Meller <yosefm@gmail.com>
License:                     GNU GENERAL PUBLIC LICENSE
Classifier: Development Status :: 5 - Production/Stable
Classifier: Intended Audience :: Science/Research
Classifier: License :: OSI Approved :: BSD License
Classifier: Programming Language :: Python :: 3
Classifier: Programming Language :: Python :: 3.8
Classifier: Programming Language :: Python :: 3.9
Classifier: Programming Language :: Python :: 3.10
Classifier: Programming Language :: Python :: 3.11
Classifier: Topic :: Scientific/Engineering
Requires-Python: >=3.8
License-File: LICENSE.txt
Requires-Dist: numpy
Requires-Dist: scipy
Requires-Dist: tables
Dynamic: author
Dynamic: home-page
Dynamic: license-file
Dynamic: requires-python
